{
  "type": "app",
  "name": "Newsfeed",
  "id": "savantly-newsfeed-module",
  "info": {
    "description": "Provide newsfeed APIs and UI components",
    "author": {
      "name": "Jeremy Branham",
      "url": "https://savantly.net"
    },
    "keywords": ["savantly", "sprout", "newsfeed"],
    "logos": {
      "small": "./plugin/img/logo.svg",
      "large": "./plugin/img/logo.svg"
    },
    "links": [
      {
        "name": "Website",
        "url": "https://github.com/savantly-net/sprout-platform/tree/development/backend/modules/newsfeed"
      },
      {
        "name": "License",
        "url": "https://github.com/savantly-net/sprout-platform/tree/development/backend/modules/newsfeed/LICENSE"
      }
    ],
    "screenshots": [],
    "version": "%VERSION%",
    "updated": "%TODAY%"
  },
  "includes": [],
  "dependencies": {
    "sproutVersion": "2.0.x",
    "plugins": []
  }
}
